{
  "Tank": {
    "skill_priority": {
      "ADDSHIELD": 20,
      "TAUNT": 20,
      "ADDPDEF": 10,
      "PHYSICDAMAGE": 5
    },
    "target_rule_enemy": "HIGHEST_ATK", 
    "target_rule_ally": "LOW_HP"
  },

  "DPS": {
    "skill_priority": {
      "CONSUME_MARK": 30,
      "PHYSICDAMAGE": 10,
      "MAGICDAMAGE": 10,
      "ADDPATK": 5
    },
    "target_rule_enemy": "WEAKEST_DEF",
    "target_rule_ally": "SELF"
  },

  "Support": {
    "skill_priority": {
      "ADDHP": 25,
      "ADDSHIELD": 15,
      "ADDPATK": 10,
      "STUN": 15
    },
    "target_rule_enemy": "RANDOM",
    "target_rule_ally": "LOW_HP"
  },

  "Default": {
    "skill_priority": {
      "PHYSICDAMAGE": 5
    },
    "target_rule": "RANDOM"
  }
}
